casbin_motor_adapter/__init__.py
casbin_motor_adapter/adapter.py
casbin_motor_adapter-0.4.0.dist-info/LICENSE.txt
casbin_motor_adapter-0.4.0.dist-info/METADATA
casbin_motor_adapter-0.4.0.dist-info/WHEEL
casbin_motor_adapter-0.4.0.dist-info/RECORD
