Metadata-Version: 2.1
Name: casbin_motor_adapter
Version: 0.4.0
Summary: Motor Adapter for PyCasbin
License: Apache-2.0
Author: wf-yamaday
Author-email: wf.yamaday.job@gmail.com
Requires-Python: >=3.8,<3.13
Classifier: License :: OSI Approved :: Apache Software License
Classifier: Programming Language :: Python :: 3
Classifier: Programming Language :: Python :: 3.8
Classifier: Programming Language :: Python :: 3.9
Classifier: Programming Language :: Python :: 3.10
Classifier: Programming Language :: Python :: 3.11
Classifier: Programming Language :: Python :: 3.12
Requires-Dist: casbin (>=1.34.0,<2.0.0)
Requires-Dist: motor (>=3.3.1,<4.0.0)
